seamm_dashboard_client/__init__.py
seamm_dashboard_client/_version.py
seamm_dashboard_client/dashboard.py
seamm_dashboard_client-2024.6.27.dist-info/AUTHORS.rst
seamm_dashboard_client-2024.6.27.dist-info/LICENSE
seamm_dashboard_client-2024.6.27.dist-info/METADATA
seamm_dashboard_client-2024.6.27.dist-info/WHEEL
seamm_dashboard_client-2024.6.27.dist-info/top_level.txt
seamm_dashboard_client-2024.6.27.dist-info/zip-safe
seamm_dashboard_client-2024.6.27.dist-info/RECORD
